{
"type": "FeatureCollection",
"name": "Export 34255-182011",
"crs": { "type": "name", "properties": { "name": "urn:ogc:def:crs:OGC:1.3:CRS84" } },
"features": [
{ "type": "Feature", "properties": { "Bol Number": "SMLU6169646A", "Arrival Date": "2020-06-08", "Company Name": "Double Green Wholesale", "Supplier Name": "Dmers Exportaciones Srl", "Product Description": "Bxs Cont Red Hot Peppers Bxs Cont Finger Hot Chilli Bxs Cont Green Thai Chilly Bxs Cont Dosakai Bxs Cont Indian Long Squash Sks Cont Coconuts", "Destination Port": "Miami, Fl", "DESTINATION PORT_1": "MIAMI, FL", "Departure Port": "Puerto Plata", "DEPARTURE PORT_1": "PUERTO PLATA", "Supplier Country": "Dominican Republic", "TEU": 2.0, "Weight": 92826, "osm_type": "relation", "display_name": "Puerto Plata, Dominican Republic", "place_id": "283455258", "class": "boundary", "type": "administrative", "road": null, "village": null, "city_district": null, "town": null, "city": null, "state": "Puerto Plata", "country": "Dominican Republic", "postcode": null }, "geometry": { "type": "Point", "coordinates": [ -70.720833835257736, 19.7225234 ] } },
{ "type": "Feature", "properties": { "Bol Number": "CLAMCOSN2M801849", "Arrival Date": "2022-11-21", "Company Name": "Double Green Wholesale", "Supplier Name": "Vegetales De Comayagua S A De C V", "Product Description": "Squash Eggplant Reefer Chinese Eggplant Long Squash Temp Vent Open Cos", "Destination Port": "Port Everglades, Fl", "DESTINATION PORT_1": "PORT EVERGLADES, FL", "Departure Port": "Puerto Cortes", "DEPARTURE PORT_1": "PUERTO CORTES", "Supplier Country": "Honduras", "TEU": 2.0, "Weight": 182011, "osm_type": "relation", "display_name": "Puerto Cortés, Cortés, 21301, Honduras", "place_id": "287067705", "class": "boundary", "type": "administrative", "road": null, "village": null, "city_district": null, "town": null, "city": "Puerto Cortés", "state": "Cortés", "country": "Honduras", "postcode": "21301" }, "geometry": { "type": "Point", "coordinates": [ -87.9426681, 15.851465 ] } },
{ "type": "Feature", "properties": { "Bol Number": "SMLU6830780A", "Arrival Date": "2021-11-05", "Company Name": "Double Green Wholesale", "Supplier Name": "Martin Lopez Export Eirl", "Product Description": "Bxs Contbread Fruit Bxs Contchinese Eggplant Sacks Contdry Coconut Contcucumber Contindian Bitter Melon Bxs Contindian Squashbxs Cont Chinesse Eggplants Saks Cont Dry Coconuts Bxs Contindin Squash Contlong Chilly Bxs Cont Small Chilli", "Destination Port": "Miami, Fl", "DESTINATION PORT_1": "MIAMI, FL", "Departure Port": "Puerto Plata", "DEPARTURE PORT_1": "PUERTO PLATA", "Supplier Country": "Dominican Republic", "TEU": 3.0, "Weight": 34255, "osm_type": "relation", "display_name": "Puerto Plata, Dominican Republic", "place_id": "283455258", "class": "boundary", "type": "administrative", "road": null, "village": null, "city_district": null, "town": null, "city": null, "state": "Puerto Plata", "country": "Dominican Republic", "postcode": null }, "geometry": { "type": "Point", "coordinates": [ -70.720833835257736, 19.7225234 ] } }
]
}
