{
"type": "FeatureCollection",
"name": "Double Green Wholesale",
"crs": { "type": "name", "properties": { "name": "urn:ogc:def:crs:OGC:1.3:CRS84" } },
"features": [
{ "type": "Feature", "properties": { "field_1": "3", "field_2": "141 Chrystie St, New York, New York, 10002", "field_3": "-73.99319882", "field_4": "40.7197665", "field_5": "Wholesale", "field_6": "Double Green", "field_7": "141 Chrystie St.", "field_8": "Manhattan", "field_9": "B", "field_10": "300 N Krome Ave, Florida City, FL 33034", "field_11": "1", "field_12": "1", "field_13": "1", "field_14": "0", "field_15": "0", "field_16": "0", "field_17": "0", "field_18": "0", "field_19": "0", "field_20": "0", "field_21": "0", "field_22": "0", "field_23": "0", "field_24": "0", "field_25": "0", "field_26": "0", "field_27": "0", "field_28": "0", "osm_type": "way", "display_na": "141, Chrystie Street, Manhattan Community Board 3, Manhattan, New York County, New York, 10002, United States", "place_id": "15483786", "class": "building", "type": "yes", "road": "Chrystie Street", "village": null, "city_distr": null, "town": null, "city": "New York", "state": "New York", "country": "United States", "postcode": "10002", "Color": null }, "geometry": { "type": "Point", "coordinates": [ -73.993338295773214, 40.7197979 ] } }
]
}
